bunting/__init__.py
bunting-0.1.4.dist-info/LICENSE
bunting-0.1.4.dist-info/WHEEL
bunting-0.1.4.dist-info/METADATA
bunting-0.1.4.dist-info/RECORD
