Metadata-Version: 2.1
Name: bunting
Version: 0.1.4
Summary: SDK for geospatial APIs like OpenStreetMap and Census
Author: Brendan Ashworth
Author-email: brendan@buntinglabs.com
Requires-Python: >=3.4,<4.0
Classifier: Programming Language :: Python :: 3
Classifier: Programming Language :: Python :: 3.4
Classifier: Programming Language :: Python :: 3.5
Classifier: Programming Language :: Python :: 3.6
Classifier: Programming Language :: Python :: 3.7
Classifier: Programming Language :: Python :: 3.8
Classifier: Programming Language :: Python :: 3.9
Classifier: Programming Language :: Python :: 3.10
Classifier: Programming Language :: Python :: 3.11
